good_interface
