Metadata-Version: 2.1
Name: good-interface
Version: 1.0.1
Summary: Provides the Interface class and other interface utilities.
Home-page: https://www.github.org/andydevs/good-handlers
Author: Anshul Kharbanda
Author-email: akanshul97@gmail.com
License: UNKNOWN
Platform: UNKNOWN
